luogu/__init__.py
luogu/constants.py
luogu/exceptions.py
luogu/session.py
luogu/utils.py
luogu/models/__init__.py
luogu/models/main.py
luogu/models/paste.py
luogu-0.1.0.dist-info/LICENSE
luogu-0.1.0.dist-info/METADATA
luogu-0.1.0.dist-info/WHEEL
luogu-0.1.0.dist-info/top_level.txt
luogu-0.1.0.dist-info/RECORD
