Metadata-Version: 2.1
Name: luogu
Version: 0.1.0
Summary: A model-based Python implement for Luogu API client
Home-page: https://github.com/piterator-org/pyluogu
Author: 汪心禾
Author-email: wangxinhe06@gmail.com
License: UNKNOWN
Project-URL: Bug Tracker, https://github.com/piterator-org/pyluogu/issues
Project-URL: Documentation, https://pyluogu.readthedocs.io/
Platform: UNKNOWN
Classifier: Programming Language :: Python :: 3
Classifier: License :: OSI Approved :: MIT License
Classifier: Operating System :: OS Independent
Requires-Python: >=3.6
License-File: LICENSE
Requires-Dist: requests
Provides-Extra: img
Requires-Dist: pillow ; extra == 'img'
